PaperCrawlerUtil/__init__.py
PaperCrawlerUtil/application.py
PaperCrawlerUtil/common_util.py
PaperCrawlerUtil/constant.py
PaperCrawlerUtil/crawler_util.py
PaperCrawlerUtil/database_util.py
PaperCrawlerUtil/document_util.py
PaperCrawlerUtil/global_val.py
PaperCrawlerUtil/log_util.py
PaperCrawlerUtil/proxypool/__init__.py
PaperCrawlerUtil/proxypool/scheduler.py
PaperCrawlerUtil/proxypool/setting.py
PaperCrawlerUtil/proxypool/crawlers/__init__.py
PaperCrawlerUtil/proxypool/crawlers/base.py
PaperCrawlerUtil/proxypool/crawlers/__pycache__/__init__.cpython-39.pyc
PaperCrawlerUtil/proxypool/crawlers/__pycache__/base.cpython-39.pyc
PaperCrawlerUtil/proxypool/crawlers/private/__init__.py
PaperCrawlerUtil/proxypool/crawlers/private/__pycache__/__init__.cpython-39.pyc
PaperCrawlerUtil/proxypool/crawlers/public/__init__.py
PaperCrawlerUtil/proxypool/crawlers/public/daili66.py
PaperCrawlerUtil/proxypool/crawlers/public/data5u.py
PaperCrawlerUtil/proxypool/crawlers/public/fatezero.py
PaperCrawlerUtil/proxypool/crawlers/public/goubanjia.py
PaperCrawlerUtil/proxypool/crawlers/public/ihuan.py
PaperCrawlerUtil/proxypool/crawlers/public/ip3366.py
PaperCrawlerUtil/proxypool/crawlers/public/ip89.py
PaperCrawlerUtil/proxypool/crawlers/public/iphai.py
PaperCrawlerUtil/proxypool/crawlers/public/jiangxianli.py
PaperCrawlerUtil/proxypool/crawlers/public/kuaidaili.py
PaperCrawlerUtil/proxypool/crawlers/public/seofangfa.py
PaperCrawlerUtil/proxypool/crawlers/public/taiyangdaili.py
PaperCrawlerUtil/proxypool/crawlers/public/xiaoshudaili.py
PaperCrawlerUtil/proxypool/crawlers/public/xicidaili.py
PaperCrawlerUtil/proxypool/crawlers/public/xiladaili.py
PaperCrawlerUtil/proxypool/crawlers/public/yqie.py
PaperCrawlerUtil/proxypool/crawlers/public/zhandaye.py
PaperCrawlerUtil/proxypool/crawlers/public/__pycache__/__init__.cpython-39.pyc
PaperCrawlerUtil/proxypool/crawlers/public/__pycache__/daili66.cpython-39.pyc
PaperCrawlerUtil/proxypool/crawlers/public/__pycache__/data5u.cpython-39.pyc
PaperCrawlerUtil-0.1.39.dist-info/LICENSE
PaperCrawlerUtil-0.1.39.dist-info/METADATA
PaperCrawlerUtil-0.1.39.dist-info/WHEEL
PaperCrawlerUtil-0.1.39.dist-info/top_level.txt
PaperCrawlerUtil-0.1.39.dist-info/RECORD
