Metadata-Version: 2.1
Name: PaperCrawlerUtil
Version: 0.1.39
Summary: a collection of utils
Home-page: https://github.com/Liwu-di/PaperCrawlerUtil
Author: liwudi@liwudi.fun
Author-email: a154125960@gmail.com
License: UNKNOWN
Platform: UNKNOWN
Classifier: Programming Language :: Python :: 3
Classifier: License :: OSI Approved :: MIT License
Classifier: Operating System :: OS Independent
Requires-Python: >=3.6
License-File: LICENSE
Requires-Dist: aiohttp (==3.8.1)
Requires-Dist: attr (==0.3.1)
Requires-Dist: attrs (==20.3.0)
Requires-Dist: beautifulsoup4 (==4.11.1)
Requires-Dist: environs (==9.5.0)
Requires-Dist: fake-headers (==1.0.2)
Requires-Dist: fake-useragent (==1.1.1)
Requires-Dist: Flask (==1.1.4)
Requires-Dist: gevent (==21.12.0)
Requires-Dist: googletrans (==4.0.0rc1)
Requires-Dist: loguru (==0.6.0)
Requires-Dist: lxml (==4.9.0)
Requires-Dist: pdf2docx (==0.5.4)
Requires-Dist: pdfplumber (==0.7.1)
Requires-Dist: pyquery (==1.4.3)
Requires-Dist: requests (==2.28.1)
Requires-Dist: retrying (==1.3.3)
Requires-Dist: setuptools (==61.2.0)
Requires-Dist: tornado (==6.1)
Requires-Dist: redis (==3.5.3)
Requires-Dist: markupsafe (==2.0.1)
Requires-Dist: PyPDF2 (==2.4.2)
Requires-Dist: tqdm (==4.64.0)
Requires-Dist: PyExecJS2 (==1.6.1)
Requires-Dist: xlrd (==2.0.1)
Requires-Dist: xlwt (==1.3.0)
Requires-Dist: pymysql (==1.0.2)
Requires-Dist: sshtunnel (==0.4.0)
